fero/__init__.py
fero/analysis.py
fero/asset.py
fero/client.py
fero/common.py
fero/datasource.py
fero/exceptions.py
fero/process.py
fero/workspace.py
fero-2.2.8.dist-info/METADATA
fero-2.2.8.dist-info/WHEEL
fero-2.2.8.dist-info/top_level.txt
fero-2.2.8.dist-info/RECORD
