Metadata-Version: 2.1
Name: fero
Version: 2.2.8
Summary: Python client for accessing Fero API
Home-page: https://github.com/FeroLabs/fero_client
Project-URL: Bug Reports, https://github.com/pypa/sampleproject/issues
Project-URL: Source, https://github.com/pypa/sampleproject/
Classifier: Intended Audience :: Developers
Classifier: Topic :: Software Development :: Build Tools
Classifier: License :: OSI Approved :: MIT License
Classifier: Programming Language :: Python :: 3
Classifier: Programming Language :: Python :: 3.7
Classifier: Programming Language :: Python :: 3.8
Classifier: Programming Language :: Python :: 3 :: Only
Requires-Python: >=3.7, <4
Requires-Dist: requests
Requires-Dist: pandas<3,>=2.2.0
Requires-Dist: marshmallow<3.16.0,>=3.8.0
Requires-Dist: azure-storage-blob
Requires-Dist: pyarrow<20.0.0,>=12.0.0
